MANIFEST.in
README
setup.py
tsunami-create
tsunami/__init__.py
tsunami/application.py
tsunami/commands.py
tsunami/logging.json
tsunami/route.py
tsunami/uimethods.py
tsunami/uimodules.py
tsunami.egg-info/PKG-INFO
tsunami.egg-info/SOURCES.txt
tsunami.egg-info/dependency_links.txt
tsunami.egg-info/requires.txt
tsunami.egg-info/top_level.txt
tsunami/clients/__init__.py
tsunami/clients/topapi.py
tsunami/clients/wangyi.py
tsunami/clients/weibo.py
tsunami/clients/xiami.py
tsunami/resources/.hgignore
tsunami/resources/appsample.py
tsunami/resources/setup.py
tsunami/resources/appsample/.DS_Store
tsunami/resources/appsample/__init__.py
tsunami/resources/appsample/models.py
tsunami/resources/appsample/services.py
tsunami/resources/appsample/web/__init__.py
tsunami/resources/appsample/web/uimethods.py
tsunami/resources/appsample/web/uimodules.py
tsunami/resources/appsample/web/static/jquery-1.7.2.min.js
tsunami/resources/appsample/web/templates/index.html
tsunami/resources/appsample/web/templates/uimodules/.DS_Store
tsunami/resources/appsample/web/templates/uimodules/paginator.html
tsunami/resources/appsample/web/views/__init__.py
tsunami/runtime/__init__.py
tsunami/runtime/db.py
tsunami/utils/__init__.py
tsunami/utils/captcha.py
tsunami/utils/chunked.py
tsunami/utils/flash.py
tsunami/utils/jsonrpc.py
tsunami/utils/nocache.py
tsunami/utils/paginator.py
tsunami/utils/restrpc.py
tsunami/utils/upload.py
tsunami/utils/fonts/FreeMonoBoldOblique.ttf
tsunami/utils/fonts/FreeSerifBoldItalic.ttf
tsunami/utils/fonts/Vera.ttf
tsunami/utils/fonts/VeraBI.ttf
tsunami/utils/fonts/VeraIt.ttf
tsunami/utils/fonts/VeraMoBI.ttf
tsunami/utils/fonts/VeraSe.ttf