Metadata-Version: 1.1
Name: tsunami
Version: 0.2
Summary: Web framework based tornado
Home-page: http://www.tsangpo.net/
Author: tsangpo
Author-email: tsangpozheng@gmail.com
License: UNKNOWN
Keywords: web framework tornado
Platform: UNKNOWN
Provides: tsunami
